{
  "text": "Baroid Industrial Drilling Products\n\n1. Введение\n- Презентация Baroid IDP (Тюмень, 2005) посвящена буровым растворам, их роли в предотвращении проблем при бурении и зависимости от геологии, инструментов и объема раствора. Буровые растворы предназначены для предотвращения проблем, а не для их решения, что экономичнее.\n\n2. Геология и типы грунтов\n- Грунты делятся на:\n  - Крупнозернистые (песок, щебень, скала): инертные, нереактивные, не набухают, не становятся липкими. Проблемы: механические (пористость, проницаемость). Решения: бентонит (например, BORE-GEL, 25–60 кг/м³ из 'MUD MUSTER conv.xls') и полимеры (QUIK-TROL, NO-SAG).\n  - Мелкозернистые (глина, суглинки): реактивные, набухают, становятся липкими. Проблемы: химические (набухание, липкость). Решения: полимеры (EZ-MUD, CON-DET, PENETROL, AQUACLEAR PFD).\n- Универсальных грунтов нет, поэтому буровые растворы и инструменты подбираются под конкретные условия.\n\n3. Буровые растворы\n- Вода не оптимальна без добавок. Добавки (бентонит, полимеры) улучшают свойства раствора:\n  - Бентонит (например, AQUAGEL, QUIK-GEL, BORE-GEL): создает фильтровальный пирог, обеспечивает суспензию и вязкость. Пластины бентонита (диаметр 1–2 микрона, толщина 1 молекула) требуют качественного смешивания.\n  - Полимеры:\n    - QUIK-TROL, QUIK-TROL LV, PAC-R, FILTER-CHEK: оптимизируют фильтровальный пирог.\n    - NO-SAG, BARA-LIFT: повышают прочность геля, создают молекулярную сетку для удержания грунта.\n    - EZ-MUD, CON-DET, PENETROL: нейтрализуют липкость и набухание глин (CON-DET и PENETROL создают отрицательный заряд или нейтрализуют заряд глины).\n    - AQUACLEAR PFD: полимер с низким молекулярным весом для разжижения.\n    - DINOMUL: жидкий воск для смазки и улучшения фильтровального пирога.\n- Идеальные свойства раствора: фильтровальный пирог, прочность геля, вязкость, близкая к воде. Высокая вязкость с высоким содержанием грунта снижает текучесть.\n\n4. Резаки и расширители\n- Резаки (например, ОКУЛА, карбидные, износостойкие) и расширители (Fluted Reamers, Helical, Super Helical, Barrel Reamer, Kodiak, Wing Cutters, Wagon Wheel) отвечают за:\n  - Управляемость буровой головки (резаки на позициях 12:00, 3:00, 6:00, 9:00).\n  - Перемешивание грунта с раствором для создания текучей суспензии.\n- Универсальных резаков и расширителей нет, выбор зависит от грунта.\n\n5. Объем бурового раствора\n- Формула: Объем (л/м) = Диаметр расширителя (дюймы)² ÷ 2.\n- Примеры:\n  - 150 мм (~6 дюймов): 6² ÷ 2 = 18 л/м (0.018 м³/м).\n  - 200 мм (~8 дюймов): 8² ÷ 2 = 32 л/м (0.032 м³/м).\n  - 250 мм (~10 дюймов): 10² ÷ 2 = 50 л/м (0.05 м³/м).\n  - 300 мм (~12 дюймов): 12² ÷ 2 = 72 л/м (0.072 м³/м).\n- Альтернативная формула: Объем (галлонов/фут) = Диаметр (дюймы)² ÷ 24.5.\n- Пример применения: для 8-дюймового расширителя и 4-дюймовой трубы с насосом 28 л/мин и скоростью протаскивания 1.5 мин/штанга требуется 42 л/штанга, но при 5 мин/штанга — 140 л/штанга. Циркуляция критически важна.\n\n6. Практический пример\n- Проблема: подрядчик застревает из-за недостаточного объема раствора или неподходящего состава (например, 2 мешка BORE-GEL на 1140 л для песка). Решение: точные данные о грунте, растворе, инструментах и объеме (например, 112 л/штанга для песка, 44 л/штанга для трубы, 42 л/штанга раствора, но без циркуляции возникают проблемы).\n- Рекомендация: использовать 'квадрат бурения' (грунт, раствор, инструмент, объем, циркуляция).\n\n7. Дополнительная информация\n- Для консультаций обращайтесь в службу поддержки Halliburton.",
  "metadata": {
    "file_name": "Презентация Baroid 1 часть.ppt, Презентация Baroid 2 часть.ppt",
    "sections_count": 7,
    "section_1": "Введение",
    "section_2": "Геология и типы грунтов",
    "section_3": "Буровые растворы",
    "section_4": "Резаки и расширители",
    "section_5": "Объем бурового раствора",
    "section_6": "Практический пример",
    "section_7": "Дополнительная информация"
  }
}