{
  "text": "Baroid Industrial Drilling Products Presentation\n\n1. Что такое бентонит?\n- Бентонит – это глина, содержащая более 70% монтмориллонита (высокодисперсный слоистый алюмосиликат).\n- Глины с содержанием монтмориллонита менее 70% относятся к бентонитоподобным.\n\n2. Состав бентонита\n- Типовой химический состав, %:\n  - Al2O3: 16.55\n  - K2O: 0.92\n  - SiO2: 52.30\n  - Na2O: 1.92\n  - TiO2: 0.95\n  - P2O5: 0.12\n  - CaO: 5.49\n  - MgO: 3.03\n  - Fe2O3: 5.20\n  - S: 0.36\n\n3. Немного истории (1)\n- Первые буровые растворы: смесь воды и глины, твердые частицы которой долго находятся во взвешенном состоянии.\n- С 1920 года растворы, утяжеленные баритом, имели недостаточную вязкость и структурные свойства для устойчивого удержания частиц барита.\n- Началась обработка раствора химическими реагентами для повышения вязкости и предотвращения осаждения утяжелителя.\n\n4. Немного истории (2)\n- Бентонит (по месторождению Бентон, США) – природный глинистый минерал, разбухающий при гидратации.\n- Впервые использовался фермерами США как гидроизоляция для удержания влаги в почве после дождя или полива.\n\n5. Бентонит (натриевый) – это вязкость и прочность геля\n\n6. Типы бентонита\n- Кальциевый: низкая степень набухания.\n- Натриевый: высокая степень набухания.\n- В России добывают кальциевые бентониты.\n\n7. Сравнение типов бентонита\n- Выход из 1 т глины – качественный показатель (свойство разбухания при гидратации).\n- Натриевые бентониты (вайомингский): 15–16 м³/т.\n- Кальциевые бентониты: 4.8–9 м³/т.\n\n8. Распускание бентонитов\n- Натриевые бентониты: 0% (0 ч), 270% (0.5 ч), 330% (1 ч), 340% (3 ч), 350% (5 ч), 355% (11–12 ч).\n- Кальциевые бентониты: 0% (0 ч), 125% (0.5 ч), 145% (1–12 ч).\n\n9. Натриевый бентонит\n- Разбухает в 15–16 раз при полной гидратации благодаря строению кристаллической решетки.\n- Основа продуктов Halliburton (Baroid-IDP).\n\n10. BORE-GEL®\n- Преимущества:\n  - Минимизирует количество продуктов для буровых растворов.\n  - Легко смешивается и быстро приготавливается.\n  - Низкая вязкость снижает давление насоса.\n  - Обеспечивает смазываемость при прокладке продуктопроводов.\n  - Сертифицирован по NSF/ANSI 60.\n  - Подходит для водозаборных скважин и несцементированных пластов.\n- Применение:\n  - Оптимальное СНС при минимальной вязкости для удаления шлама.\n  - Уменьшение фильтрации за счет тонкой глинистой корки низкой проницаемости.\n  - Повышение стабильности ствола в песчаниках и гравии.\n  - Смазка труб при проходке туннелей малого диаметра.\n- Рецептура:\n  - Нормальные условия: 15–42 кг/м³.\n  - Слабоуплотненные пласты: 42–72 кг/м³.\n  - Туннели малого диаметра: 60–72 кг/м³.\n\n11. TUNNEL-GEL PLUS®\n- Преимущества:\n  - Легко замешивается, быстро достигает максимальной вязкости.\n  - Повышает смазывающую способность, снижая тяговое усилие.\n  - Производит в 2+ раза больше раствора аналогичной вязкости по сравнению с API-бентонитами.\n- Применение:\n  - Увеличение вязкости в пресной воде.\n  - Эффективная выносная способность и свойства суспензии.\n  - Контроль фильтрации в грунт, стабильность бурового канала.\n  - Смазка в микротуннелировании.\n- Рецептура: 15–35 кг/м³ (стандартные условия).",
  "metadata": {
    "file_name": "2 Presentation ab Bentonite.ppt",
    "sections_count": 11,
    "section_1": "Что такое бентонит?",
    "section_2": "Состав Бентонита",
    "section_3": "Немного истории (1)",
    "section_4": "Немного истории (2)",
    "section_5": "Бентонит (натриевый) – это вязкость и прочность геля",
    "section_6": "Типы бентонита",
    "section_7": "Сравнение типов бентонита",
    "section_8": "Распускание бентонитов",
    "section_9": "Натриевый бентонит",
    "section_10": "BORE-GEL®",
    "section_11": "TUNNEL-GEL PLUS®"
  }
}