{
  "text": "Baroid Industrial Drilling Products Presentation\n\nConfidentiality: Confidential - For Internal Use Only. © 2005 Halliburton. All Rights Reserved.\n\n1. Загрязнители\n- Вещества, оказывающие внешнее влияние, которые мешают свойствам бурового раствора или разрушают их.\n\n2. Загрязнители\n- Соль\n- Хлор\n- Кальций\n- Шлам\n- Вода/Температура\n- Лигниты/Фосфаты/Дерево\n\n3. Две фазы проблем\n- Загрязнители изначально в воде.\n- Загрязнители, сталкивающиеся в процессе бурения.\n\n4. Соль\n- Электролит.\n- Ингибирует гидратацию (разбухание бентонита).\n\n5. Соль (определение)\n- Легко определить тестом:\n  - Титрование.\n  - Проба на вкус.\n\n6. Соль (обработка)\n- Соль ничем не убирается.\n- Найти другой источник воды.\n\n7. Соль (решение)\n- Некоторые материалы можно смешать в соленой воде.\n- Специально для соленой воды разработан бентонит TUNNEL-GEL™ SW.\n\n8. TUNNEL-GEL™ SW\n- Создает стабильность ствола скважины.\n- Улучшает шламо-выносную способность.\n- Способствует развитию фильтрационной корки.\n\n9. Соль (рекомендация)\n- Лучше найти другой источник воды.\n\n10. Хлор\n- Разрушает цепочку полимеров.\n- Тесты:\n  - Тестовые палочки.\n  - Запах.\n\n11. Хлор (обработка)\n- Кальцинированная сода.\n- Перемешивание.\n\n12. Соль и хлор (определение)\n- Соль: на вкус.\n- Хлор: на запах.\n\n13. Скрытые загрязнители\n- Невозможно определить на вкус и запах.\n- Кальций (Ca++), также называется жесткостью воды.\n\n14. Кальций и pH\n- Кальций устраняется поднятием pH до 8.5–9.5 с помощью кальцинированной соды.\n\n15. Кальций (обработка)\n- Кальцинированная сода поднимает pH и убирает кальций.\n\n16. Механизм устранения кальция\n- Химическая реакция с добавлением кальцинированной соды.\n\n17. Шлам\n- Нежелательна рециркуляция шлама.\n\n18. Вода\n- Песок имеет пористость и проницаемость.\n- Пористость: поровые пространства между частицами песка.\n- Проницаемость: связанные поровые пространства.\n\n19. Вода (в бурении)\n- При бурении ниже водяных горизонтов поровые пространства наполняет вода.\n\n20. Лигниты/Фосфаты/Органические вещества\n- Лигниты, фосфаты, дерево используются как разжижители бурового раствора.\n- Могут уходить в землю, вызывая эффект разжижения в скважине.\n\n21. Температура\n- Время реакции:\n  - В теплой воде: меньше.\n  - В холодной воде: больше.\n- Параметры (холодная/теплая вода):\n  - 600 rpm: 37/43\n  - 300 rpm: 25/34\n  - PV: 12/9\n  - YP: 13/25\n  - 10 sec Gel: 9/13\n  - 10 min Gel: 14/18\n  - Filtrate, cc: 12/12",
  "metadata": {
    "file_name": "6 Contaminants.ppt",
    "sections_count": 21,
    "section_1": "Загрязнители",
    "section_2": "Список загрязнителей",
    "section_3": "Две фазы проблем",
    "section_4": "Соль",
    "section_5": "Соль (определение)",
    "section_6": "Соль (обработка)",
    "section_7": "Соль (решение)",
    "section_8": "TUNNEL-GEL™ SW",
    "section_9": "Соль (рекомендация)",
    "section_10": "Хлор",
    "section_11": "Хлор (обработка)",
    "section_12": "Соль и хлор (определение)",
    "section_13": "Скрытые загрязнители",
    "section_14": "Кальций и pH",
    "section_15": "Кальций (обработка)",
    "section_16": "Механизм устранения кальция",
    "section_17": "Шлам",
    "section_18": "Вода",
    "section_19": "Вода (в бурении)",
    "section_20": "Лигниты/Фосфаты/Органические вещества",
    "section_21": "Температура"
  }
}