{
  "text": "Baroid Industrial Drilling Products Presentation\n\nConfidentiality: Confidential - For Internal Use Only. © 2005 Halliburton. All Rights Reserved.\n\n1. Буровой Раствор\n- Что такое буровой раствор? Вода\n\n2. Буровой Раствор\n- Вода не создает свойств бурового раствора\n\n3. Песок\n- Пористый и проницаемый\n\n4. Глины и Сланцы\n- Становятся липкими и/или разбухают\n\n5. Буровой Раствор\n- Реагенты добавляются, чтобы вода стала удобной для использования\n\n6. Буровой Раствор\n- Реагенты разработаны для предотвращения проблем, а не для их решения\n\n7. Буровой Раствор\n- Решение проблемы дорого, предотвращение экономичнее\n\n8. Основы квадрата\n- Геология – Грунты\n- Рецептура раствора\n- Буровой инструмент\n- Объем бурового раствора\n\n9. Квадрат бурения\n- Свойства грунта\n\n10. Грунт\n- Нет универсальных грунтов\n\n11. Типы грунтов\n- Крупнозернистые: песок, щебень, скала\n- Мелкозернистые: глина, сланцы (суглинки)\n\n12. Крупнозернистые грунты\n- Пористость и проницаемость\n- Инертные и нереактивные\n- Не набухают и не становятся липкими\n- Создают механические проблемы, требуют механических решений\n\n13. Крупнозернистые грунты\n- Бентонит\n\n14. Песок\n- Вода на песке (демонстрация фильтрации)\n- После 5 секунд\n- После 14 секунд\n- После 35 секунд\n- После 45 секунд\n- После 1 минуты\n- После 1:18 минуты\n- После 1:26 минуты\n- После 2:11 минуты\n- После 2:43 минуты\n\n15. Бентонит с полимером\n- После 19 секунд\n- После 30 секунд\n- После 1:46 секунд\n- После 3:17 секунд\n- После 7 минут\n- После 8 минут\n- После 24 часов\n\n16. Бентонит используют в...\n- Крупнозернистые грунты\n\n17. Крупнозернистые грунты\n- Бентонит с полимерными добавками\n- Образование фильтрационной корки\n- QUIK-TROL, QUIK-TROL LV, QUIK-TROL GOLD, QUIK-TROL GOLD LV, FILTER-CHEK\n\n18. Улучшение фильтрационной корки\n- Бентонит пластины\n- Quik-Trol пластины\n\n19. Полимерные добавки\n- Прочность геля: NO-SAG, BARAZAN\n\n20. NO-SAG\n- Имеет мелкое тело с усиками\n- Усики раскрываются при низком потоке\n- Большие концентрации: густая суспензия\n- Низкие концентрации: низкая суспензия\n\n21. Гельность\n- Демонстрация осадка песка\n- После 17 секунд\n- После 32 секунд\n- После 2:08 минут\n- После 8:22 минут\n\n22. Добавляем NO-SAG\n- После 41 секунд\n- После 1:05 минут\n- Нет осадка\n\n23. Мелкозернистые грунты\n- Ингибирование глин и защита от налипания\n- EZ-MUD, EZ-MUD GOLD, QUIK-MUD, PENETROL, AQUACLEAR® PFD\n\n24. EZ-MUD\n- Мономеры образуют линейный полимер\n\n25. AQUACLEAR® PFD\n- Полимер с экстремально низким молекулярным весом\n\n26. Мелкозернистые грунты\n- Реактивные, разбухают и становятся липкими\n- Меняются в зависимости от содержания влаги\n- Продукты: EZ-MUD, EZ-MUD GOLD, QUIK-MUD GOLD, PENETROL, CONDET\n\n27. Мелкозернистые грунты\n- Химические проблемы требуют химических решений\n- Бентонит + EZ-MUD GOLD\n\n28. Разбухание\n- Площадь бурового канала\n- Площадь частиц грунта\n\n29. Грунты\n- Нет универсальных грунтов, поэтому нет универсальных буровых растворов\n\n30. Квадрат бурения\n- Тип грунта\n- Буровой раствор\n\n31. Резаки и Расширители\n- Должны хорошо служить режущим инструментом\n\n32. Резаки\n- Мягкие грунты: окула, упрочненный резак, твердосплавное лезвие\n- Карбидовый резак, твердый сплав, жесткий резак, жесткая головка\n- Резаки отвечают за управляемость буровой головки\n- Управление достигается вращением лопатки\n\n33. Расширители\n- Функции: режущий инструмент, перемешивание грунта с раствором для текучей суспензии\n- Типы: рифленые, винтовые, супер винтовые, барный резак, крыльчатые, барельный, открыватель ствола, раскалывающий резак\n\n34. Резаки и Расширители\n- Нет универсальных грунтов, поэтому нет универсальных резаков и расширителей\n\n35. Квадрат бурения\n- Свойства грунтов, буровой раствор, резаки/расширители\n\n36. Объем бурового раствора\n- Нет универсальных грунтов, поэтому нет универсального объема бурового раствора\n\n37. Объем бурового раствора\n- Расчет: Диаметр расширителя (дюймы)² ÷ 2 = литр/метр грунта\n- Примеры: 150 мм (18 л/м), 200 мм (32 л/м), 250 мм (50 л/м), 300 мм (72 л/м)\n\n38. Квадрат бурения\n- Инструмент, раствор, тип грунта, объем раствора, циркуляция\n\n39. Что нам нужно?\n- Буровой раствор, смазочное средство, жидкость для стабилизации грунта, строительный раствор, все вышеперечисленное\n- Бентонитовые пластинки: каждая песчинка – пачка пластинок",
  "metadata": {
    "file_name": "3 European Drilling Square russian.ppt",
    "sections_count": 39,
    "section_1": "Буровой Раствор",
    "section_2": "Буровой Раствор (вода не создает свойств)",
    "section_3": "Песок",
    "section_4": "Глины и Сланцы",
    "section_5": "Буровой Раствор (реагенты)",
    "section_6": "Буровой Раствор (предотвращение проблем)",
    "section_7": "Буровой Раствор (экономия)",
    "section_8": "Основы квадрата",
    "section_9": "Квадрат бурения",
    "section_10": "Грунт",
    "section_11": "Типы грунтов",
    "section_12": "Крупнозернистые грунты",
    "section_13": "Крупнозернистые грунты (бентонит)",
    "section_14": "Песок",
    "section_15": "Бентонит с полимером",
    "section_16": "Бентонит используют в...",
    "section_17": "Крупнозернистые грунты (полимеры)",
    "section_18": "Улучшение фильтрационной корки",
    "section_19": "Полимерные добавки",
    "section_20": "NO-SAG",
    "section_21": "Гельность",
    "section_22": "Добавляем NO-SAG",
    "section_23": "Мелкозернистые грунты",
    "section_24": "EZ-MUD",
    "section_25": "AQUACLEAR® PFD",
    "section_26": "Мелкозернистые грунты (реактивные)",
    "section_27": "Мелкозернистые грунты (химические решения)",
    "section_28": "Разбухание",
    "section_29": "Грунты",
    "section_30": "Квадрат бурения (тип грунта)",
    "section_31": "Резаки и Расширители",
    "section_32": "Резаки",
    "section_33": "Расширители",
    "section_34": "Резаки и Расширители (универсальность)",
    "section_35": "Квадрат бурения (свойства грунтов)",
    "section_36": "Объем бурового раствора",
    "section_37": "Объем бурового раствора (расчет)",
    "section_38": "Квадрат бурения (инструмент)",
    "section_39": "Что нам нужно?"
  }
}