{
  "text": "Baroid Industrial Drilling Products Presentation\n\n1. Определение свойств раствора\n- Почему важно определять свойства раствора?\n- Чтобы получить нужные свойства\n- Чтобы поддерживать эти свойства\n- Для выявления и решения проблем\n- Ведение записей свойств\n\n2. Свойства\n- Вязкость\n- Плотность\n- Фильтрационные свойства\n- Реология\n- Содержание песка\n- pH\n- Кальций\n\n3. Плотность\n- Плотность (вес) раствора\n- Измеряется рычажными весами (Baroid Mud Balance)\n- Процесс: наливаем раствор с избытком, закрываем крышку, убираем лишний раствор, устанавливаем на точку опоры, регулируем ползунок до равновесия\n- Записываем плотность (г/см³ или lb/gal)\n- Калибровка весов водой (1 г/см³)\n- Используется для расчета гидростатического давления и содержания выбуренного грунта\n- Допустимый предел: как можно ниже\n\n4. Расчет гидростатического давления\n- Давление (kPa) = плотность (kg/m³) × глубина (m) × 0.00981\n- Пример: 1198.7 kg/m³ × 221 m × 0.00981 = 2598.8 kPa\n- Альтернатива: вес раствора (ppg) × 0.052 × глубина (футы) = давление (PSI)\n\n5. Расчет содержания шлама\n- % Шлама = (Плотность (г/см³) - 1) × 60\n- Пример: (1.4 - 1) × 60 = 24% шлама\n- Альтернатива: (Вес раствора, ppg - 8.33) × 8 = % Шлама\n\n6. Регулирование плотности\n- Растет при добавлении утяжеляющих агентов\n- Снижается при разбавлении водой и рециркуляции\n- Baroid рекомендует снижать плотность\n\n7. Вязкость\n- Сопротивление течению\n- Измеряется воронкой Марша (сек/л) или реометром\n- Воронка Марша: измеряет густоту, не связана с прочностью геля или фильтрацией\n- Процесс: наполнить воронку до 1500 мл, измерить время наполнения литровой кружки\n- Нормальные значения: 45–75 сек/л\n- Высокая вязкость увеличивает давление на насосе\n- Низкая вязкость поддерживает свойства суспензии\n- Вязкость воды: 26 сек/л при 21.1°C\n\n8. Регулирование вязкости\n- Повышается загустителями (бентонит, полимеры)\n- Понижается разжижителями (вода, дисперсанты)\n- Относительный тест, показывает изменение свойств\n\n9. Реологические свойства\n- Измеряются полевым реометром\n- Процесс: прикрутить рукав, наполнить кружку, опустить рукав до отметки, использовать скорости 1100, 600, 300 rpm\n- Пластическая вязкость: зависит от размера, формы и количества частиц, желательно минимальная\n- Динамическое напряжение сдвига (ДНС): способность нести частицы, важный показатель\n\n10. Прочность геля (СНС)\n- Измеряет гелевую структуру в покое\n- Процесс: остановить реометр, отсчитать 10 сек, 10 мин или 30 мин, медленно вращать (3 rpm), записать максимальное значение\n- Измеряется в Па или фунт/100 фут²\n\n11. Содержание песка\n- Измеряется набором для определения песка (% по объему)\n- Процесс: налить раствор до метки, добавить воду, взболтать, вылить через 200-меш сетку, промыть, перелить песок обратно в колбу\n- Песок: частицы >74 микрон\n- Показывает абразивность раствора\n- Желаемый предел: ≤1% по объему\n\n12. Фильтрация\n- Измеряет объем фильтрата и толщину фильтрационной корки\n- Используется API фильтр-пресс (половинная площадь)\n- Измеряется: мл/30 мин, толщина корки (мм или 1/32 дюйма)\n- Процесс: установить резиновый стаканчик, налить раствор, положить фильтровальную бумагу, закрутить крышку, установить картридж CO2, перевернуть пресс, открыть клапан, установить давление 100 PSI, измерить фильтрат за 7.5 мин, умножить объем и толщину на 4 для 30 мин\n\n13. Механизм фильтрации\n- Проникновение фильтрата, образование корки в проницаемых формациях\n- Полимеры: физическое закупоривание пор, адсорбция/инкапсуляция, загущение водной фазы\n\n14. Проблемы при высокой фильтрации\n- Увеличенная площадь соприкосновения, толстая корка\n- Низкая фильтрация (≤15 мл) обеспечивает тонкую, плотную корку\n\n15. pH\n- Кислотность или щелочность (0–14, 7 – нейтральная)\n- Измеряется pH-полосками, лакмусовой бумагой или pH-метром\n- Желаемый pH: 8.5–9.5\n- Повышение: кальцинированная сода\n- Понижение (при загрязнении цементом): бикарбонат натрия\n\n16. Кальций\n- Жесткость воды, затрудняет распускание бентонита и полимеров\n- Измеряется полосками или титрованием (mg/l, ppm)\n- Процесс: опустить полоску в воду, сравнить цвет\n- Удаление: кальцинированная сода\n- Желаемый уровень: <100 ppm\n\n17. Очистка канала\n- Расчет: Диаметр канала (дюйм)² ÷ 2 = литров/метр грунта\n- Производительность насоса (л/мин) × мин/штангу = литров раствора\n- Литры грунта + литры раствора = общий объем\n- Литры грунта ÷ общий объем = % шлама\n- Пример (12” расширитель, 240 л/мин, 3 мин/штангу, 4.57 м штанги, плотность 1.38 г/см³): 72 л/м грунта, 720 л раствора, 216 л грунта, 936 л общего объема, 23% шлама\n- Фактическое содержание: (1.38 – 1) × 60 = 22.8%\n\n18. Проблемы очистки канала\n- Проверка размера резака/расширителя, плотности, пересчет % шлама\n- Проверка прочности геля, добавление бентонита, BARAZAN, NO-SAG\n- Проблема при 42% шлама: промывка или толстая фильтрационная корка",
  "metadata": {
    "file_name": "7 Fluids Testing half area filter press.ppt",
    "sections_count": 18,
    "section_1": "Определение свойств раствора",
    "section_2": "Свойства",
    "section_3": "Плотность",
    "section_4": "Расчет гидростатического давления",
    "section_5": "Расчет содержания шлама",
    "section_6": "Регулирование плотности",
    "section_7": "Вязкость",
    "section_8": "Регулирование вязкости",
    "section_9": "Реологические свойства",
    "section_10": "Прочность геля (СНС)",
    "section_11": "Содержание песка",
    "section_12": "Фильтрация",
    "section_13": "Механизм фильтрации",
    "section_14": "Проблемы при высокой фильтрации",
    "section_15": "pH",
    "section_16": "Кальций",
    "section_17": "Очистка канала",
    "section_18": "Проблемы очистки канала"
  }
}