{
  "text": "Baroid Industrial Drilling Products Presentation\n\nConfidentiality: Confidential - For Internal Use Only. © 2005 Halliburton. All Rights Reserved.\n\n1. Что такое ГНБ?\n- Бестраншейный метод укладки труб\n- Экономия денег\n- Соблюдение экологических норм\n- Минимальное время строительства\n- Подход 21 века\n\n2. Немного истории про ГНБ\n- Задумки о востребованности ГНБ с середины 60-х в США\n- Первый проект в 1971 году: укладка газопровода под р. Паджеро (Калифорния)\n- Длина 231 м, диаметр 115 мм\n- Первая публикация в 1972 году\n- К 1992 году пробурено 2400 переходов методом ГНБ\n\n3. ГНБ в наши дни\n- Значительный рост мощности и функциональности\n- Высокое развитие автоматизации и улучшенных механизмов\n- Рынок насыщен оборудованием для любых проектных потребностей\n- Ежегодное обновление и создание новых модификаций машин\n\n4. 4 важных элемента для ГНБ\n- Геология\n- Инструмент\n- Концентрации\n- Объемы\n\n5. Значение раствора в ГНБ\n- Стабильность ствола скважины\n- Формирование фильтрационной корки\n- Обеспечение смазывающих характеристик\n- Транспортировка выбуренной породы\n- Ингибирование всех видов глин\n- Экономия денег\n\n6. Что такое раствор\n- Строительный материал\n- Состав: вода + кальцинированная сода\n- Бентонит\n- Полимеры\n- Специальная химия\n\n7. Важные качества раствора\n- Высокие реологические характеристики\n- Хорошие показатели водоотдачи\n- Стабильность канала\n- Вынос шлама на поверхность\n- Сокращение сроков выполнения работ\n- Экономия денег\n- Уверенность в дальнейших проектах\n\n8. Функции бентонита в растворе\n- Смазка\n- Образование вязкости\n- Контроль фильтрации\n- Создание структуры\n- Стабильность ствола скважины\n\n9. Функции полимеров в растворе\n- Стабилизация глин/сланцев\n- Образование вязкости\n- Контроль фильтрации\n- Суспензия\n- Стабильность ствола\n- Образование фильтрационной корки\n- Смазка\n\n10. Преимущества Baroid IDP\n- История более 50 лет\n- Высокая устойчивость к загрязнениям\n- Высокая производительность\n- Сертификация по стандартам NSF/ANSI 60\n- Отличная совместимость продуктов без негативных реакций\n- Высокодисперсные и не ферментируемые материалы\n- Уверенность в завтрашнем дне\n\n11. Подход к делу Baroid IDP\n- Оказание сервиса для всех клиентов\n- Покрытие всей географии России и СНГ\n- Сопровождение больших проектов по запросу заказчика\n- Быстрая логистика\n- Возможность покупки в удобном регионе\n- Помощь с нормативной и процессуальной документацией (МСДС, гидравлические сертификаты и т.д.)\n\n12. Продукция Baroid IDP\n- [No specific products listed]",
  "metadata": {
    "file_name": "1 Presentation HDD.ppt",
    "sections_count": 12,
    "section_1": "Что такое ГНБ?",
    "section_2": "Немного истории про ГНБ",
    "section_3": "ГНБ в наши дни",
    "section_4": "4 важных элемента для ГНБ",
    "section_5": "Значение раствора в ГНБ",
    "section_6": "Что такое раствор",
    "section_7": "Важные качества раствора",
    "section_8": "Функции бентонита в растворе",
    "section_9": "Функции полимеров в растворе",
    "section_10": "Преимущества Baroid IDP",
    "section_11": "Подход к делу Baroid IDP",
    "section_12": "Продукция Baroid IDP"
  }
}