{
  "text": "Baroid Industrial Drilling Products Presentation\n\nConfidentiality: Confidential - For Internal Use Only. © 2005 Halliburton. All Rights Reserved.\n\n1. Возможность правильного смешивания\n- Полное использование добавок в буровом растворе.\n- Увеличивается производительность бурового раствора.\n- Исключает возможность присутствия нераспустившихся бентонитов и полимеров.\n- Большая отдача ожидаемого результата.\n\n2. Требования к буровому раствору\n- Очень важно изначально обработать воду, очистить от загрязнителей.\n- Адекватное смесительное оборудование.\n- Соответствующие концентрации продуктов.\n- Каждый продукт эффективен даже в малых концентрациях.\n- Контроль за свойствами бурового раствора: жесткость, плотность, вязкость, pH, водоотдача.\n\n3. Существенное перемешивание\n- Обработать изначально воду и очистить от загрязнителей.\n- Бентонит должен иметь адекватный сдвиг и время для гидратации и выхода раствора.\n- Полимеры должны иметь адекватное перемешивание и время для конечного выхода.\n\n4. Обработка воды до необходимых свойств\n- Кальций (жесткость): <100 mg/l.\n- Хлориды (соль): <500 mg/l.\n- Хлор (с муниципальных источников): <100 mg/l.\n\n5. Обработка и удаление загрязнителей\n- Кальций: кальцинированная сода (0.6–2.4 kg/m³).\n- Хлориды: при высоком уровне искать другой источник воды; если вторичный источник соленый, подобрать продукты, терпимые к соленой воде.\n- Хлор: вода может быть газированной, хлор улетучивается в атмосферу.\n\n6. Соответствующее смешивание бурового раствора\n- Порядок добавления:\n  1. Кальцинированная сода.\n  2. Бентонит.\n  3. Полимеры (сухие, затем жидкие).\n  4. Сурфактанты (с небольшим перемешиванием).\n  5. Разжижители и продукты против потери циркуляции, если необходимо.\n- QUIK-TROL полимеры добавлять перед семейством EZ-MUD.\n\n7. Требования к системе приготовления\n- Система должна производить эффективный сдвиг.\n- Смесительное оборудование обеспечивает высокое количество энергии в системе.\n\n8. Лопата как миксер?\n- Без лопаты в зоне перемешивания.\n\n9. Для бентонита\n- Система смешивания должна производить эффективный сдвиг.\n- Энергия для превращения бентонита из агрегированного состояния в пластинки с помощью дисперсионной воды.\n- Увеличение площади поверхности бентонита за счет подпиточной воды ускоряет гидратацию.\n\n10. Смешивание и требования к бентониту\n- Адекватная обработка воды.\n- Сдвиг.\n- Время.\n\n11. Для полимеров\n- Система смешивания должна производить эффективный сдвиг.\n- Жидкие полимеры: сдвиг для разрушения эмульсии и гидратации в системе жидкости.\n- Сухие полимеры: сдвиг в обработанной воде для сокращения комков и эффективной гидратации.\n- Увеличение площади поверхности полимеров в обработанной воде для улучшения потока и гидратации.\n\n12. Требования смешивания для полимеров\n- Сухие полимеры: меньший сдвиг, длительное время разбавления для гидратации.\n- Жидкие полимеры: больший сдвиг, меньшее время разбавления.\n- Медленное и последовательное добавление для всех полимеров.\n\n13. Смешивание сухих полимеров\n- Медленно добавлять, чтобы избежать комков.\n\n14. Высокообъемная воронка Вентури\n- Используется для эффективного смешивания.\n\n15. Система регенерации\n- Поддерживает качество бурового раствора.\n\n16. Погружные смесители\n- Обеспечивают дополнительное перемешивание.\n\n17. EZ-MUD® GOLD\n- Добавляется через воронку Вентури.\n\n18. Предварительная смесительная система\n- Обеспечивает подготовку раствора перед использованием.\n\n19. Обращение с продуктом\n- Безопасность – главный приоритет.\n- Обратитесь к MSDS (листы данных по безопасности материалов) для информации о:\n  - Безопасном использовании, хранении, перевозке.\n  - Потенциальной опасности и чрезвычайных контактах.\n  - Оборудовании для защиты персонала (PPE).\n- Средства защиты должны использоваться эффективно.\n- Респиратор (N95): фильтрует 95% частиц ≥0.3 мкм.\n- При сомнениях – приоритет безопасности.\n\n20. Базовая защита\n- Использовать респираторы N95 при добавлении продуктов в раствор.\n- Защита глаз обязательна и должна быть соответствующей.\n\n21. Обращение с продуктом – ВНИМАНИЕ!\n- Каустическую соду не использовать.\n- Причины:\n  - Образует высокий pH.\n  - Может прожигать полимеры.\n  - Используется в специфических направлениях.\n  - Требует специального оборудования и тренингов.\n\n22. Что следует помнить\n- Предварительно обработать воду.\n- Адекватное смесительное оборудование.\n- Корректный выбор продуктов и концентраций.\n- Соблюдать порядок добавления.\n- Контролировать свойства буровой жидкости.\n- Безопасная обработка и использование средств защиты.\n\n23. Организация и забота о работе\n- Использовать воронку, емкости, тестер, кальцинированную соду, продукцию.",
  "metadata": {
    "file_name": "5 Mixing & Handling.ppt",
    "sections_count": 23,
    "section_1": "Возможность правильного смешивания",
    "section_2": "Требования к буровому раствору",
    "section_3": "Существенное перемешивание",
    "section_4": "Обработка воды до необходимых свойств",
    "section_5": "Обработка и удаление загрязнителей",
    "section_6": "Соответствующее смешивание бурового раствора",
    "section_7": "Требования к системе приготовления",
    "section_8": "Лопата как миксер?",
    "section_9": "Для бентонита",
    "section_10": "Смешивание и требования к бентониту",
    "section_11": "Для полимеров",
    "section_12": "Требования смешивания для полимеров",
    "section_13": "Смешивание сухих полимеров",
    "section_14": "Высокообъемная воронка Вентури",
    "section_15": "Система регенерации",
    "section_16": "Погружные смесители",
    "section_17": "EZ-MUD® GOLD",
    "section_18": "Предварительная смесительная система",
    "section_19": "Обращение с продуктом",
    "section_20": "Базовая защита",
    "section_21": "Обращение с продуктом – ВНИМАНИЕ!",
    "section_22": "Что следует помнить",
    "section_23": "Организация и забота о работе"
  }
}