{
  "text": "Baroid Industrial Drilling Products\n\n1. Идентификация продукта\n- Название: TUNNEL-GEL PLUS™.\n- Производитель: Halliburton.\n- Описание: Высокопродуктивный гелевый загуститель для буровых растворов (см. '2 Presentation ab Bentonite.json' для рецептуры: 20–35 кг/м³).\n\n2. Меры первой помощи\n- Вдыхание: Переместить в зону свежего воздуха. Обратиться к врачу при раздражении дыхательных путей или затрудненном дыхании.\n- Кожа: Промыть с мылом и водой. Обратиться к врачу при сохраняющемся раздражении.\n- Глаза: Промыть большим количеством воды не менее 15 минут. Обратиться к врачу при сохраняющемся раздражении.\n- Проглатывание: При нормальных условиях меры первой помощи не требуются.\n- Примечания для врача: Лечить симптоматически.\n\n3. Меры пожаротушения\n- Подходящие средства: Все стандартные средства пожаротушения.\n- Неподходящие средства: Неизвестны.\n- Особые опасности: Не применимо.\n- Защитное оборудование для пожарных: Не применимо.\n\n4. Меры при случайном высвобождении\n- Личные меры предосторожности: Использовать защитное оборудование, избегать вдыхания пыли.\n- Экологические меры: Неизвестны.\n- Процедура очистки: Собирать без пыли и хранить для утилизации. Учитывать возможные токсичные или пожарные риски от загрязняющих веществ.\n\n5. Обращение и хранение\n- Обращение: Содержит кварц, кристобалит и/или тридимит, которые могут быть в воздухе без видимого облака. Избегать пыли, использовать вентиляцию, носить респиратор (NIOSH, EN 149 или эквивалент). Материал скользкий во влажном состоянии.\n- Хранение: Поддерживать чистоту в рабочих зонах, закрывать контейнер, не использовать повторно. Срок годности: 12 месяцев.\n\n6. Контроль воздействия и средства защиты\n- Технические меры: Использовать промышленную вентиляцию и локальный отвод для соблюдения пределов воздействия.\n- Респиратор: NIOSH, EN 149 или эквивалент.\n- Защита рук: Рабочие перчатки.\n- Защита кожи: Подходящая одежда, стирать пыльную одежду перед повторным использованием.\n- Защита глаз: Защитные очки или маска.\n\n7. Физические и химические свойства\n- Физическое состояние: Порошок.\n- Цвет: От коричнево-бежевого до серого.\n- Запах: Легкий землистый.\n- pH: 8–10.\n- Удельный вес (20°C, вода=1): 2.65.\n- Растворимость в воде: Диспергируется.\n- Процент летучих веществ: 8–12%.\n- Другие параметры (плотность, температура кипения, вязкость и т.д.): Не определены.\n\n8. Стабильность и реакционная способность\n- Стабильность: Стабилен.\n- Опасная полимеризация: Не происходит.\n- Условия избегания: Не ожидаются.\n- Несовместимость: Фтористоводородная кислота.\n- Продукты разложения: Аморфный кремнезем может трансформироваться в тридимит (870°C) или кристобалит (1470°C).\n\n9. Токсикологическая информация\n- Основные пути воздействия: Контакт с глазами, кожей, вдыхание.\n- Вдыхание: Кристаллический кремнезем (кварц, кристобалит) канцерогенен для человека (IARC Group 1), тридимит — возможный канцероген (IARC Group 2A). Может вызывать раздражение носа, горла, дыхательных путей. Хроническое воздействие может привести к силикозу (кашель, одышка, снижение функции легких), усугубляемому курением, и повысить риск туберкулеза, склеродермы и заболеваний почек.\n- Кожа: Может вызывать механическое раздражение.\n- Глаза: Может вызывать раздражение.\n- Проглатывание: Эффекты неизвестны.\n- Хронические эффекты: Силикоз, канцерогенность (IARC Group 1 для кварца/кристобалита, Group 2A для тридимита, ACGIH A2 для кварца).\n- Усугубляемые состояния: Респираторные заболевания (астма, бронхит), раздражение глаз.\n\n10. Регуляторная информация\n- Инвентарь EINECS: Продукт и компоненты соответствуют EINECS.\n- Классификация опасности для воды (Германия): WGK 0 (не представляет опасности для воды).\n\n11. Дополнительная информация\n- Для дополнительной информации по использованию обращайтесь к представителю Halliburton.\n- Для вопросов по MSDS: Chemical Compliance, тел. 1-580-251-4335.\n- Отказ от ответственности: Информация предоставлена без гарантий точности или полноты. Пользователь отвечает за определение пригодности материала.",
  "metadata": {
    "file_name": "TUNNELGEL PLUS SDS.pdf",
    "sections_count": 11,
    "section_1": "Идентификация продукта",
    "section_2": "Меры первой помощи",
    "section_3": "Меры пожаротушения",
    "section_4": "Меры при случайном высвобождении",
    "section_5": "Обращение и хранение",
    "section_6": "Контроль воздействия и средства защиты",
    "section_7": "Физические и химические свойства",
    "section_8": "Стабильность и реакционная способность",
    "section_9": "Токсикологическая информация",
    "section_10": "Регуляторная информация",
    "section_11": "Дополнительная информация"
  }
}