{
  "text": "Baroid Industrial Drilling Products\n\n1. Описание продукта\n- Название: TUNNEL-GEL PLUS™.\n- Описание: Специально разработанный высокопродуктивный бентонит для туннельного бурения и горизонтально-направленного бурения (HDD) большого диаметра. Обеспечивает быстрое развитие вязкости, эффективную стабилизацию бурового канала и улучшенный контроль фильтрации в большинстве водных буровых растворов.\n\n2. Применение и функции\n- Способствует:\n  - Улучшенному развитию вязкости в пресноводных буровых растворах.\n  - Эффективной транспортировке и суспензии выбуренной породы.\n  - Улучшенному контролю фильтрации и стабилизации бурового канала.\n  - Эффективной смазке для микротуннелирования.\n\n3. Преимущества\n- Легко смешивается и быстро достигает максимальной вязкости.\n- Увеличивает смазывающие свойства раствора, снижая требуемые усилия для продавливания.\n- Обеспечивает более чем вдвое больший выход бурового раствора той же вязкости по сравнению с бентонитом стандарта API при равной концентрации.\n\n4. Типичные свойства\n- Внешний вид: Порошок от желтого до коричнево-бежевого цвета.\n- Удельный вес: 2.6 г/см³.\n- pH (3% раствор): 10.4.\n\n5. Рекомендации по обработке\n- Для оптимального выхода и производительности предварительно обработать воду кальцинированной содой (0.5–1.0 кг/м³) для снижения жесткости кальция до ≤100 мг/л и регулировки pH до 8.5–9.5.\n- Добавлять TUNNEL-GEL PLUS™ медленно и равномерно через воронку Вентури или коллоидный смеситель в циркуляционную систему или смесительный резервуар.\n- Рекомендуемые концентрации: 25–35 кг/м³ (20–30 фунтов/100 галлонов или 8.4–12.6 фунтов/баррель).\n\n6. Упаковка\n- Упакован в многослойные бумажные мешки по 25 кг (55.1 фунта).\n\n7. Доступность\n- Доступен только через европейских розничных продавцов Baroid Industrial Drilling Products. Для получения информации о ближайшем продавце обратитесь в службу поддержки клиентов Halliburton.",
  "metadata": {
    "file_name": "TUNNEL_GEL_PLUS conv.docx",
    "sections_count": 7,
    "section_1": "Описание продукта",
    "section_2": "Применение и функции",
    "section_3": "Преимущества",
    "section_4": "Типичные свойства",
    "section_5": "Рекомендации по обработке",
    "section_6": "Упаковка",
    "section_7": "Доступность"
  }
}